standards/__init__.py
standards/dialect.py
standards/package.py
standards/resource.py
standards/schema.py
standards/standard.py
standards/assets/VERSION
standards/formats/__init__.py
standards/formats/ckan/__init__.py
standards/formats/ckan/mapper.py
standards/formats/ckan/package.py
standards/formats/ckan/resource.py
frictionless_standards-2.0.0a1.dist-info/LICENSE.md
frictionless_standards-2.0.0a1.dist-info/METADATA
frictionless_standards-2.0.0a1.dist-info/WHEEL
frictionless_standards-2.0.0a1.dist-info/entry_points.txt
frictionless_standards-2.0.0a1.dist-info/top_level.txt
frictionless_standards-2.0.0a1.dist-info/RECORD
